pyPBS_EL/__init__.py
pyPBS_EL/main.py
pyPBS_EL-1.0.6.data/scripts/pyPBS_EL
pyPBS_EL-1.0.6.dist-info/LICENSE
pyPBS_EL-1.0.6.dist-info/METADATA
pyPBS_EL-1.0.6.dist-info/WHEEL
pyPBS_EL-1.0.6.dist-info/top_level.txt
pyPBS_EL-1.0.6.dist-info/RECORD
