Metadata-Version: 2.1
Name: pyPBS-EL
Version: 1.0.6
Summary: Package for distribution
Home-page: 
Download-URL: 
Author: msjeon27
Author-email: msjeon27@cau.ac.kr
Keywords: PYPBSEL,pypbsel
Classifier: Programming Language :: Python :: 3
Classifier: License :: OSI Approved :: MIT License
Classifier: Operating System :: OS Independent
Requires-Python: >=3.6
License-File: LICENSE
Requires-Dist: argparse
